mpl_stereo/AxesStereo.py
mpl_stereo/StereoSquare.py
mpl_stereo/__init__.py
mpl_stereo/data/church_left.jpg
mpl_stereo/data/church_left_cropped.jpg
mpl_stereo/data/church_right.jpg
mpl_stereo/data/sun_left.png
mpl_stereo/data/sun_right.png
mpl_stereo/example_data.py
mpl_stereo-0.11.0.dist-info/WHEEL
mpl_stereo-0.11.0.dist-info/METADATA
mpl_stereo-0.11.0.dist-info/RECORD
