Metadata-Version: 2.4
Name: mpl-stereo
Version: 0.11.0
Summary: See your matplotlib plots in 3D by making stereograms and anaglyphs
Author: Scott Shambaugh
Author-email: Scott Shambaugh <scottshambaugh@users.noreply.github.com>
License-Expression: MIT
Classifier: Framework :: Matplotlib
Classifier: Operating System :: OS Independent
Classifier: Topic :: Scientific/Engineering :: Visualization
Classifier: Topic :: Multimedia :: Graphics :: 3D Rendering
Classifier: Programming Language :: Python :: 3
Classifier: Programming Language :: Python :: 3 :: Only
Classifier: Programming Language :: Python :: 3.10
Classifier: Programming Language :: Python :: 3.11
Classifier: Programming Language :: Python :: 3.12
Classifier: Programming Language :: Python :: 3.13
Classifier: Programming Language :: Python :: 3.14
Requires-Dist: matplotlib>=3.10.0
Requires-Dist: numpy>=1.26
Requires-Python: >=3.10, <4
